hatch_fancy_pypi_readme/__init__.py
hatch_fancy_pypi_readme/__main__.py
hatch_fancy_pypi_readme/_builder.py
hatch_fancy_pypi_readme/_cli.py
hatch_fancy_pypi_readme/_config.py
hatch_fancy_pypi_readme/_fragments.py
hatch_fancy_pypi_readme/_substitutions.py
hatch_fancy_pypi_readme/exceptions.py
hatch_fancy_pypi_readme/hooks.py
hatch_fancy_pypi_readme/py.typed
hatch_fancy_pypi_readme-23.2.0.dist-info/METADATA
hatch_fancy_pypi_readme-23.2.0.dist-info/WHEEL
hatch_fancy_pypi_readme-23.2.0.dist-info/entry_points.txt
hatch_fancy_pypi_readme-23.2.0.dist-info/licenses/AUTHORS.md
hatch_fancy_pypi_readme-23.2.0.dist-info/licenses/LICENSE.txt
hatch_fancy_pypi_readme-23.2.0.dist-info/RECORD
